hipack.py
hipack-14.data/scripts/hipack
hipack-14.dist-info/METADATA
hipack-14.dist-info/WHEEL
hipack-14.dist-info/top_level.txt
hipack-14.dist-info/RECORD
