Metadata-Version: 2.1
Name: hipack
Version: 14
Summary: Serialization library or the HiPack interchange format
Home-page: https://github.com/aperezdc/hipack-python
Author: Adrian Perez de Castro
Author-email: aperez@igalia.com
License: Dual GPL3 / MIT
Classifier: Development Status :: 4 - Beta
Classifier: Intended Audience :: Developers
Classifier: Natural Language :: English
Classifier: License :: OSI Approved :: GNU General Public License v3 (GPLv3)
Classifier: License :: OSI Approved :: MIT License
Classifier: Programming Language :: Python :: 3
Classifier: Programming Language :: Python :: 3.3
Classifier: Programming Language :: Python :: 3.4
Classifier: Programming Language :: Python :: 3.5
Classifier: Programming Language :: Python :: 3.11
Classifier: Programming Language :: Python
Classifier: Operating System :: OS Independent
